{
    "status":"SUCCESS",
    "meta":{
       "confidence_level":"High",
       "disclaimer":"Based on 10 months of consistent data. Highly reliable baseline.",
       "months_analyzed":10
    },
    "metrics":{
       "total_baseline_spend":16257.222865079364,
       "personal_inflation_rate":1.9711285442555873,
       "monthly_inflation_tax":320.45076039682533
    },
    "breakdown":[
       {
          "category":"Payments",
          "baseline_spend":3550.725,
          "inflation_rate":3.0,
          "inflation_tax":106.52175
       },
       {
          "category":"CreditCard Payment",
          "baseline_spend":849.1666666666666,
          "inflation_rate":3.0,
          "inflation_tax":25.474999999999998
       },
       {
          "category":"Rates",
          "baseline_spend":799.0099999999999,
          "inflation_rate":3.0,
          "inflation_tax":23.970299999999995
       },
       {
          "category":"Grocery",
          "baseline_spend":367.116,
          "inflation_rate":6.5,
          "inflation_tax":23.86254
       },
       {
          "category":"MISC",
          "baseline_spend":741.4069999999999,
          "inflation_rate":3.0,
          "inflation_tax":22.242209999999996
       },
       {
          "category":"Insurance",
          "baseline_spend":692.728,
          "inflation_rate":3.0,
          "inflation_tax":20.78184
       },
       {
          "category":"Fruits/Veg",
          "baseline_spend":479.60200000000003,
          "inflation_rate":3.0,
          "inflation_tax":14.388060000000001
       },
       {
          "category":"COSTCO",
          "baseline_spend":384.75666666666666,
          "inflation_rate":3.0,
          "inflation_tax":11.5427
       },
       {
          "category":"Electricity",
          "baseline_spend":374.92999999999995,
          "inflation_rate":3.0,
          "inflation_tax":11.247899999999998
       },
       {
          "category":"EATERY",
          "baseline_spend":259.73100000000005,
          "inflation_rate":3.0,
          "inflation_tax":7.791930000000002
       },
       {
          "category":"Petrol",
          "baseline_spend":226.02399999999997,
          "inflation_rate":3.0,
          "inflation_tax":6.780719999999999
       },
       {
          "category":"Savings",
          "baseline_spend":224.128,
          "inflation_rate":3.0,
          "inflation_tax":6.723839999999999
       },
       {
          "category":"Shopping",
          "baseline_spend":243.2211111111111,
          "inflation_rate":2.5,
          "inflation_tax":6.080527777777778
       },
       {
          "category":"Water",
          "baseline_spend":142.757,
          "inflation_rate":3.0,
          "inflation_tax":4.28271
       },
       {
          "category":"Education",
          "baseline_spend":119.734,
          "inflation_rate":3.0,
          "inflation_tax":3.5920199999999998
       },
       {
          "category":"Mobile/Internet",
          "baseline_spend":101.673,
          "inflation_rate":3.0,
          "inflation_tax":3.0501899999999997
       },
       {
          "category":"Withdrawals",
          "baseline_spend":94.28571428571429,
          "inflation_rate":3.0,
          "inflation_tax":2.8285714285714287
       },
       {
          "category":"Classes",
          "baseline_spend":93.75,
          "inflation_rate":3.0,
          "inflation_tax":2.8125
       },
       {
          "category":"DIY",
          "baseline_spend":78.31,
          "inflation_rate":3.0,
          "inflation_tax":2.3493
       },
       {
          "category":"Gas",
          "baseline_spend":73.89,
          "inflation_rate":3.0,
          "inflation_tax":2.2167
       },
       {
          "category":"Meat",
          "baseline_spend":71.44222222222223,
          "inflation_rate":3.0,
          "inflation_tax":2.143266666666667
       },
       {
          "category":"Mobile",
          "baseline_spend":70.57142857142857,
          "inflation_rate":3.0,
          "inflation_tax":2.117142857142857
       },
       {
          "category":"Temple",
          "baseline_spend":60.0,
          "inflation_rate":3.0,
          "inflation_tax":1.7999999999999998
       },
       {
          "category":"MedicalCare",
          "baseline_spend":42.5,
          "inflation_rate":4.0,
          "inflation_tax":1.7
       },
       {
          "category":"Entertainment",
          "baseline_spend":54.35,
          "inflation_rate":3.0,
          "inflation_tax":1.6305
       },
       {
          "category":"Fitness",
          "baseline_spend":34.59,
          "inflation_rate":3.0,
          "inflation_tax":1.0377
       },
       {
          "category":"Gambling",
          "baseline_spend":28.375,
          "inflation_rate":3.0,
          "inflation_tax":0.85125
       },
       {
          "category":"Laundry",
          "baseline_spend":23.0,
          "inflation_rate":3.0,
          "inflation_tax":0.69
       },
       {
          "category":"Parking",
          "baseline_spend":20.2,
          "inflation_rate":3.0,
          "inflation_tax":0.606
       },
       {
          "category":"Printing",
          "baseline_spend":12.2375,
          "inflation_rate":3.0,
          "inflation_tax":0.36712500000000003
       },
       {
          "category":"EMI",
          "baseline_spend":5847.005,
          "inflation_rate":0.0,
          "inflation_tax":0.0
       },
       {
          "category":"Transport",
          "baseline_spend":86.12777777777778,
          "inflation_rate":-1.2,
          "inflation_tax":-1.0335333333333334
       }
    ]
 }